sunix_ledstrip_controller_client/__init__.py
sunix_ledstrip_controller_client/client.py
sunix_ledstrip_controller_client/controller.py
sunix_ledstrip_controller_client/functions.py
sunix_ledstrip_controller_client/packets/__init__.py
sunix_ledstrip_controller_client/packets/requests.py
sunix_ledstrip_controller_client/packets/responses.py
sunix_ledstrip_controller_client/timer.py
sunix_ledstrip_controller_client-2.0.5.dist-info/LICENSE
sunix_ledstrip_controller_client-2.0.5.dist-info/WHEEL
sunix_ledstrip_controller_client-2.0.5.dist-info/METADATA
sunix_ledstrip_controller_client-2.0.5.dist-info/RECORD
