Metadata-Version: 2.1
Name: sunix-ledstrip-controller-client
Version: 2.0.5
Summary: A library for controlling the Sunix RGB / RGBWWCW WiFi LED Strip controller
Home-page: https://github.com/markusressel/sunix-ledstrip-controller-client
License: AGPLv3+
Keywords: sunix,sunix-ledstrip-controller-client
Author: Markus Ressel
Author-email: mail@markusressel.de
Requires-Python: >=3.7,<4.0
Classifier: Development Status :: 5 - Production/Stable
Classifier: License :: OSI Approved :: GNU Affero General Public License v3 or later (AGPLv3+)
Classifier: License :: Other/Proprietary License
Classifier: Programming Language :: Python :: 3
Classifier: Programming Language :: Python :: 3 :: Only
Classifier: Programming Language :: Python :: 3.10
Classifier: Programming Language :: Python :: 3.4
Classifier: Programming Language :: Python :: 3.5
Classifier: Programming Language :: Python :: 3.6
Classifier: Programming Language :: Python :: 3.7
Classifier: Programming Language :: Python :: 3.8
Classifier: Programming Language :: Python :: 3.9
Requires-Dist: construct
Requires-Dist: typing
Project-URL: Repository, https://github.com/markusressel/sunix-ledstrip-controller-client
